odoo/addons/website_sale_extra_infos/LICENSE
odoo/addons/website_sale_extra_infos/README.rst
odoo/addons/website_sale_extra_infos/__init__.py
odoo/addons/website_sale_extra_infos/__manifest__.py
odoo/addons/website_sale_extra_infos/controllers/__init__.py
odoo/addons/website_sale_extra_infos/controllers/website.py
odoo/addons/website_sale_extra_infos/controllers/website_customer.py
odoo/addons/website_sale_extra_infos/controllers/website_params.py
odoo/addons/website_sale_extra_infos/controllers/website_patents.py
odoo/addons/website_sale_extra_infos/images/screen.png
odoo/addons/website_sale_extra_infos/models/__init__.py
odoo/addons/website_sale_extra_infos/models/attachment.py
odoo/addons/website_sale_extra_infos/models/blacklist.py
odoo/addons/website_sale_extra_infos/models/blacklist_customer.py
odoo/addons/website_sale_extra_infos/models/config.py
odoo/addons/website_sale_extra_infos/models/patent_history.py
odoo/addons/website_sale_extra_infos/models/product_template.py
odoo/addons/website_sale_extra_infos/models/res_partner.py
odoo/addons/website_sale_extra_infos/models/sale_order.py
odoo/addons/website_sale_extra_infos/models/sale_order_line.py
odoo/addons/website_sale_extra_infos/readme/CONTRIBUTORS.md
odoo/addons/website_sale_extra_infos/readme/DESCRIPTION.md
odoo/addons/website_sale_extra_infos/readme/USAGE.md
odoo/addons/website_sale_extra_infos/security/ir.model.access.csv
odoo/addons/website_sale_extra_infos/static/description/icon.png
odoo/addons/website_sale_extra_infos/static/src/js/extra_info_validation.js
odoo/addons/website_sale_extra_infos/static/src/js/one_product.js
odoo/addons/website_sale_extra_infos/views/blacklist_views.xml
odoo/addons/website_sale_extra_infos/views/block_view.xml
odoo/addons/website_sale_extra_infos/views/product_template_views.xml
odoo/addons/website_sale_extra_infos/views/res_partner_views.xml
odoo/addons/website_sale_extra_infos/views/sale_menu_views.xml
odoo/addons/website_sale_extra_infos/views/sale_order_views.xml
odoo_addon_website_sale_extra_infos-18.0.1.0.0.dist-info/METADATA
odoo_addon_website_sale_extra_infos-18.0.1.0.0.dist-info/WHEEL
odoo_addon_website_sale_extra_infos-18.0.1.0.0.dist-info/top_level.txt
odoo_addon_website_sale_extra_infos-18.0.1.0.0.dist-info/RECORD
